easytl/__init__.py
easytl/classes.py
easytl/easytl.py
easytl/exceptions.py
easytl/version.py
easytl/services/__init__.py
easytl/services/anthropic_service.py
easytl/services/azure_service.py
easytl/services/deepl_service.py
easytl/services/gemini_service.py
easytl/services/googletl_service.py
easytl/services/openai_service.py
easytl/util/__init__.py
easytl/util/constants.py
easytl/util/llm_util.py
easytl/util/util.py
easytl-0.6.0.dist-info/licenses/LICENSE.md
easytl-0.6.0.dist-info/METADATA
easytl-0.6.0.dist-info/WHEEL
easytl-0.6.0.dist-info/top_level.txt
easytl-0.6.0.dist-info/RECORD
