Metadata-Version: 2.4
Name: easytl
Version: 0.6.0
Summary: Seamless Multi-API Translation: Simplifying Language Barriers with DeepL, OpenAI, Gemini, Google Translate and More.
Author-email: "Kaden Bilyeu (Bikatr7)" <Bikatr7@proton.me>, Alejandro Mata <alemalvarez@icloud.com>
Project-URL: Homepage, https://github.com/Bikatr7/EasyTL
Project-URL: Issues, https://github.com/Bikatr7/EasyTL/issues
Project-URL: Documentation, https://easytl.readthedocs.io/en/latest/index.html
Classifier: Programming Language :: Python :: 3.10
Classifier: Programming Language :: Python :: 3.11
Classifier: Programming Language :: Python :: 3.12
Classifier: License :: OSI Approved :: GNU Lesser General Public License v2 or later (LGPLv2+)
Classifier: Operating System :: OS Independent
Requires-Python: >=3.10
License-File: LICENSE.md
Requires-Dist: google-generativeai>=0.8.3
Requires-Dist: deepl>=1.20.0
Requires-Dist: openai>=1.58.1
Requires-Dist: backoff>=2.2.1
Requires-Dist: tiktoken>=0.7.0
Requires-Dist: google-cloud-translate>=3.15.3
Requires-Dist: anthropic>=0.42.0
Requires-Dist: requests>=2.31.0
Requires-Dist: pydantic
Dynamic: license-file
